dotlinker/__init__.py
dotlinker/cli.py
dotlinker/config.py
dotlinker/model.py
dotlinker/util.py
dotlinker/backends/__init__.py
dotlinker/backends/base.py
dotlinker/backends/chezmoi.py
dotlinker/backends/cloud.py
docoli-1.0.3.dist-info/METADATA
docoli-1.0.3.dist-info/WHEEL
docoli-1.0.3.dist-info/entry_points.txt
docoli-1.0.3.dist-info/licenses/LICENSE
docoli-1.0.3.dist-info/RECORD
