Metadata-Version: 2.4
Name: docoli
Version: 1.0.3
Summary: Config linker for chezmoi and Nextcloud
Project-URL: Homepage, https://www.veen.world/
Project-URL: Repository, https://github.com/kevinveenbirkenbach/dotlinker
Author-email: Kevin Veen-Birkenbach <kevin@veen.world>
License: MIT
License-File: LICENSE
Requires-Python: >=3.10
Requires-Dist: pyyaml>=6.0
